picklecacher/__init__.py
picklecacher/picklecache.py
picklecacher_myfatemi04-0.0.1.dist-info/LICENSE
picklecacher_myfatemi04-0.0.1.dist-info/METADATA
picklecacher_myfatemi04-0.0.1.dist-info/WHEEL
picklecacher_myfatemi04-0.0.1.dist-info/top_level.txt
picklecacher_myfatemi04-0.0.1.dist-info/RECORD
