Metadata-Version: 2.1
Name: picklecacher-myfatemi04
Version: 0.0.1
Summary: A package that lets you cache your function outputs between runs
Home-page: https://github.com/myfatemi04/picklecache
Author: Michael Fatemi
Author-email: myfatemi04@gmail.com
License: UNKNOWN
Platform: UNKNOWN
Classifier: Programming Language :: Python :: 3
Classifier: License :: OSI Approved :: MIT License
Classifier: Operating System :: OS Independent
Requires-Python: >=3.6
